pipeproxy/__init__.py
pipeproxy/proxy.py
pipeproxy/lib/__init__.py
pipeproxy/lib/proxyListener/__init__.py
pipeproxy/lib/proxyListener/proxyListenerMessageReceiver.py
pipeproxy/lib/proxyListener/proxyListenerMessageSender.py
pipeproxy/lib/proxyListener/proxyListener.py
pipeproxy/lib/proxyListener/proxyListenerMessageHandler.py
pipeproxy/lib/objectProxy/__init__.py
pipeproxy/lib/objectProxy/objectProxy.py
pipeproxy/lib/objectProxy/objectProxyMaker.py
pipeproxy/lib/objectProxy/proxyMessanger/__init__.py
pipeproxy/lib/objectProxy/proxyMessanger/proxyMessageSender.py
pipeproxy/lib/objectProxy/proxyMessenger/__init__.py
pipeproxy/lib/objectProxy/proxyMessenger/proxyMessageSender.py
pipeproxy/lib/proxyMessages/__init__.py
pipeproxy/lib/proxyMessages/replyMessage.py
pipeproxy/lib/proxyMessages/requestMessage.py
test_pipeproxy/__init__.py
test_pipeproxy/test_proxy.py
test_pipeproxy/testObject.py
test_pipeproxy/test_lib/__init__.py
test_pipeproxy/test_lib/test_proxyMessages/__init__.py
test_pipeproxy/test_lib/test_proxyMessages/test_requestMessage.py
test_pipeproxy/test_lib/test_proxyMessages/test_replyMessage.py
test_pipeproxy/test_lib/test_objectProxy/test_objectProxy.py
test_pipeproxy/test_lib/test_objectProxy/test_objectProxyMaker.py
test_pipeproxy/test_lib/test_objectProxy/__init__.py
test_pipeproxy/test_lib/test_objectProxy/test_proxyMessanger/__init__.py
test_pipeproxy/test_lib/test_objectProxy/test_proxyMessanger/test_proxyMessageSender.py
test_pipeproxy/test_lib/test_objectProxy/test_proxyMessenger/__init__.py
test_pipeproxy/test_lib/test_objectProxy/test_proxyMessenger/test_proxyMessageSender.py
test_pipeproxy/test_lib/test_proxyListener/__init__.py
test_pipeproxy/test_lib/test_proxyListener/test_proxyListener.py
test_pipeproxy/test_lib/test_proxyListener/test_proxyListenerMessageSender.py
test_pipeproxy/test_lib/test_proxyListener/test_proxyListenerMessageReceiver.py
pipeproxy-0.7.dist-info/RECORD
pipeproxy-0.7.dist-info/METADATA
pipeproxy-0.7.dist-info/DESCRIPTION.rst
pipeproxy-0.7.dist-info/metadata.json
pipeproxy-0.7.dist-info/WHEEL
pipeproxy-0.7.dist-info/top_level.txt
