Metadata-Version: 1.0
Name: pipeproxy
Version: 0.7
Summary: A sort-of-proxy solution for multiprocess communication using Pipe from mulitprocessing.
Home-page: https://github.com/dRoje/pipe-proxy.git
Author: Duje Roje
Author-email: rojeduje@gmail.com
License: MIT
Platform: UNKNOWN
